aiosyncthing/__init__.py
aiosyncthing/api.py
aiosyncthing/config.py
aiosyncthing/database.py
aiosyncthing/events.py
aiosyncthing/exceptions.py
aiosyncthing/syncthing.py
aiosyncthing/system.py
aiosyncthing-0.7.1.dist-info/licenses/LICENSE
aiosyncthing-0.7.1.dist-info/METADATA
aiosyncthing-0.7.1.dist-info/WHEEL
aiosyncthing-0.7.1.dist-info/top_level.txt
aiosyncthing-0.7.1.dist-info/zip-safe
aiosyncthing-0.7.1.dist-info/RECORD
