Metadata-Version: 2.4
Name: aiosyncthing
Version: 0.7.1
Summary: Asynchronous Python client for the Syncthing REST API
Home-page: https://github.com/zhulik/aiosyncthing
Author: Gleb Sinyavskiy
Author-email: zhulik.gleb@gmail.com
License: The MIT License
Keywords: syncthing,sync,rest,backup,api,aio,async,await
Classifier: Development Status :: 4 - Beta
Classifier: Intended Audience :: Developers
Classifier: Natural Language :: English
Classifier: License :: OSI Approved :: MIT License
Classifier: Programming Language :: Python :: 3.10
Classifier: Programming Language :: Python :: 3.11
Classifier: Programming Language :: Python :: 3.12
Classifier: Programming Language :: Python :: 3.13
Classifier: Programming Language :: Python :: 3.14
Classifier: Programming Language :: Python :: 3.15
Classifier: Topic :: System :: Archiving :: Mirroring
License-File: LICENSE
Requires-Dist: aiohttp<4.0.0,>=3.7.4
Requires-Dist: yarl<2.0.0,>=1.6.3
Dynamic: author
Dynamic: author-email
Dynamic: classifier
Dynamic: description
Dynamic: description-content-type
Dynamic: home-page
Dynamic: keywords
Dynamic: license
Dynamic: license-file
Dynamic: requires-dist
Dynamic: summary
